special/__init__.py
special/chi.py
special/config.py
special/fits.py
special/mcmc_sampling.py
special/model_resampling.py
special/nested_sampling.py
special/spec_corr.py
special/spec_indices.py
special/template_fit.py
special/utils_mcmc.py
special/utils_nested.py
special/utils_spec.py
special-0.2.6.dist-info/LICENSE
special-0.2.6.dist-info/METADATA
special-0.2.6.dist-info/WHEEL
special-0.2.6.dist-info/top_level.txt
special-0.2.6.dist-info/RECORD
