Metadata-Version: 2.1
Name: special
Version: 0.2.6
Summary: Package for SPEctral Characterization of ImAged Low-mass companions
Home-page: https://github.com/VChristiaens/special
Author: Valentin Christiaens
Author-email: valentin.christiaens@uliege.be
License: MIT
Classifier: Intended Audience :: Science/Research
Classifier: License :: OSI Approved :: MIT License
Classifier: Operating System :: MacOS :: MacOS X
Classifier: Operating System :: POSIX :: Linux
Classifier: Natural Language :: English
Classifier: Programming Language :: Python :: 3.6
Classifier: Programming Language :: Python :: 3.7
Classifier: Programming Language :: Python :: 3.8
Classifier: Programming Language :: Python :: 3.9
Classifier: Topic :: Scientific/Engineering :: Astronomy
License-File: LICENSE
Requires-Dist: cython
Requires-Dist: numpy
Requires-Dist: scipy
Requires-Dist: astropy
Requires-Dist: emcee ==2.2.1
Requires-Dist: corner
Requires-Dist: nestle
Requires-Dist: ultranest
Requires-Dist: pandas
Requires-Dist: matplotlib <=3.4.3
Requires-Dist: nbsphinx
Requires-Dist: pandoc
Requires-Dist: h5py
Requires-Dist: urllib3 <2.0
